walden/__init__.py
walden/__main__.py
walden/cli.py
walden/compiler/__init__.py
walden/compiler/build.py
walden/compiler/log_generator.py
walden/journal/__init__.py
walden/journal/create_journal.py
walden/journal/edit_journal.py
walden/utils/__init__.py
walden/utils/constants.py
walden-0.0.73.dist-info/LICENSE
walden-0.0.73.dist-info/METADATA
walden-0.0.73.dist-info/WHEEL
walden-0.0.73.dist-info/entry_points.txt
walden-0.0.73.dist-info/top_level.txt
walden-0.0.73.dist-info/RECORD
