Metadata-Version: 2.1
Name: walden
Version: 0.0.73
Summary: A .tex journaling system
Home-page: https://github.com/aravindkoneru/Walden
Author: Aravind Koneru
Author-email: aravind.b.koneru@gmail.com
License: UNKNOWN
Platform: UNKNOWN
Classifier: Programming Language :: Python :: 3
Classifier: License :: OSI Approved :: MIT License
Classifier: Operating System :: OS Independent
Requires-Python: >=3.5
